Metadata-Version: 2.1
Name: Flask-Discord-Extended
Version: 0.0.3
Summary: The Python OAuth2 and Discord Bot Commands for Flask applications.
Home-page: https://github.com/davidg0022/Flask-Discord-Extended
Author: Gatea David
Author-email: davidgatea21@gmail.com
License: MIT
Platform: any
Classifier: Framework :: Flask
Classifier: Environment :: Web Environment
Classifier: Intended Audience :: Developers
Classifier: License :: OSI Approved :: MIT License
Classifier: Operating System :: OS Independent
Classifier: Programming Language :: Python
License-File: LICENSE
